chispa/__init__.py
chispa/bcolors.py
chispa/column_comparer.py
chispa/dataframe_comparer.py
chispa/default_formats.py
chispa/formatting/__init__.py
chispa/formatting/format_string.py
chispa/formatting/formats.py
chispa/formatting/formatting_config.py
chispa/number_helpers.py
chispa/row_comparer.py
chispa/rows_comparer.py
chispa/schema_comparer.py
chispa/structfield_comparer.py
chispa-0.11.0.dist-info/LICENSE.md
chispa-0.11.0.dist-info/METADATA
chispa-0.11.0.dist-info/NOTICE-binary.md
chispa-0.11.0.dist-info/WHEEL
chispa-0.11.0.dist-info/RECORD
