Metadata-Version: 2.1
Name: chispa
Version: 0.11.0
Summary: Pyspark test helper library
Home-page: https://github.com/MrPowers/chispa
License: MIT
Keywords: apachespark,spark,pyspark,pytest
Author: Matthew Powers
Author-email: matthewkevinpowers@gmail.com
Maintainer: Semyon Sinchenko
Maintainer-email: ssinchenko@apache.org
Requires-Python: >=3.8,<4.0
Classifier: Development Status :: 3 - Alpha
Classifier: Environment :: Console
Classifier: Framework :: Pytest
Classifier: Intended Audience :: Developers
Classifier: License :: OSI Approved :: MIT License
Classifier: Operating System :: OS Independent
Classifier: Programming Language :: Python
Classifier: Programming Language :: Python :: 3
Classifier: Programming Language :: Python :: 3.8
Classifier: Programming Language :: Python :: 3.9
Classifier: Programming Language :: Python :: 3.10
Classifier: Programming Language :: Python :: 3.11
Classifier: Programming Language :: Python :: 3.12
Classifier: Topic :: Software Development :: Libraries :: Python Modules
Classifier: Topic :: Software Development :: Quality Assurance
Classifier: Topic :: Software Development :: Testing
Requires-Dist: prettytable (>=3.10.2,<4.0.0)
Project-URL: Documentation, https://mrpowers.github.io/chispa
Project-URL: Repository, https://github.com/MrPowers/chispa
